setup.py
cliui/__init__.py
cliui/confirm.py
cliui/prompt.py
cliui/safedit.py
cliui/sigint.py
cliui/sudo.py
cliui.egg-info/PKG-INFO
cliui.egg-info/SOURCES.txt
cliui.egg-info/dependency_links.txt
cliui.egg-info/top_level.txt