Metadata-Version: 1.0
Name: cliui
Version: 0.0.1
Summary: utils for command line user iteraction
Home-page: https://github.com/zweifisch/cliui
Author: Feng Zhou
Author-email: zf.pascal@gmail.com
License: UNKNOWN
Platform: UNKNOWN
